inliners/__init__.py
inliners/__main__.py
inliners-1.0.6.dist-info/LICENSE.txt
inliners-1.0.6.dist-info/METADATA
inliners-1.0.6.dist-info/WHEEL
inliners-1.0.6.dist-info/top_level.txt
inliners-1.0.6.dist-info/RECORD
