Metadata-Version: 2.1
Name: inliners
Version: 1.0.6
Summary: Parse a string representing multiple strings.
Author-email: Johannes <johannes-programming@mailfence.com>
License: The MIT License (MIT)
Project-URL: Documentation, https://pypi.org/project/inliners
Project-URL: Download, https://pypi.org/project/inliners/#files
Project-URL: Source, https://github.com/johannes-programming/inliners
Classifier: License :: OSI Approved :: MIT License
Classifier: Programming Language :: Python
Classifier: Programming Language :: Python :: 3
Classifier: Programming Language :: Python :: 3 :: Only
Requires-Python: >=3.11
License-File: LICENSE.txt
Requires-Dist: click >=8.1.7
Requires-Dist: getoptify >=1.0.1
